build_meta_plus.py
build_meta_plus-0.1.2.dist-info/licenses/license.txt
build_meta_plus-0.1.2.dist-info/METADATA
build_meta_plus-0.1.2.dist-info/WHEEL
build_meta_plus-0.1.2.dist-info/top_level.txt
build_meta_plus-0.1.2.dist-info/RECORD
