Metadata-Version: 2.4
Name: build-meta-plus
Version: 0.1.2
Summary: A drop-in replacement for setuptools.build_meta that adds automated pre- and post-build hooks for cleanup and asset generation
Author-email: Ronny Rentner <build_meta_plus.code@ronny-rentner.de>
License-Expression: Apache-2.0
Project-URL: Homepage, https://github.com/ronny-rentner/build-meta-plus
Project-URL: Repository, https://github.com/ronny-rentner/build-meta-plus.git
Project-URL: Issues, https://github.com/ronny-rentner/build-meta-plus/issues
Keywords: setuptools,build_meta,build-backend,hooks,pep517,pep660,drop-in replacement,automation,cleanup,pre-build,post-build
Classifier: Development Status :: 4 - Beta
Classifier: Intended Audience :: Developers
Classifier: Topic :: Software Development :: Build Tools
Classifier: Programming Language :: Python :: 3
Classifier: Programming Language :: Python :: 3.9
Classifier: Programming Language :: Python :: 3.10
Classifier: Programming Language :: Python :: 3.11
Classifier: Programming Language :: Python :: 3.12
Classifier: Programming Language :: Python :: 3.13
Classifier: Programming Language :: Python :: 3.14
Requires-Python: >=3.9
License-File: license.txt
Requires-Dist: setuptools>=61
Dynamic: license-file
